Tikweb/TikTok.py
Tikweb/__init__.py
Tikweb/authz/__init__.py
Tikweb/authz/aws4.py
Tikweb/exceptions/__init__.py
Tikweb/exceptions/errors.py
Tikweb/utils/X_Bogus.py
Tikweb/utils/X_Gnarl.py
Tikweb/utils/__init__.py
Tikweb/utils/did.py
Tikweb/utils/generate_device.py
Tikweb/utils/ttencrypt.py
Tikweb/utils/url_encode.py
tikweb-1.0.5.dist-info/licenses/LICENSE
tikweb-1.0.5.dist-info/METADATA
tikweb-1.0.5.dist-info/WHEEL
tikweb-1.0.5.dist-info/entry_points.txt
tikweb-1.0.5.dist-info/top_level.txt
tikweb-1.0.5.dist-info/RECORD
